paf_sapgui_tc_bzv_reklaantworten/__init__.py
paf_sapgui_tc_bzv_reklaantworten/elements/zjkta_nb_rklsm.py
paf_sapgui_tc_bzv_reklaantworten/Program.cs
paf_sapgui_tc_bzv_reklaantworten/test.py
paf_sapgui_tc_bzv_reklaantworten-1.0.3.dist-info/WHEEL
paf_sapgui_tc_bzv_reklaantworten-1.0.3.dist-info/METADATA
paf_sapgui_tc_bzv_reklaantworten-1.0.3.dist-info/RECORD
