Metadata-Version: 2.1
Name: paf-sapgui-tc-bzv-reklaantworten
Version: 1.0.3
Summary: 
Author: Your Name
Author-email: you@example.com
Requires-Python: >=3.10,<4.0
Classifier: Programming Language :: Python :: 3
Classifier: Programming Language :: Python :: 3.10
Requires-Dist: paf_sapgui (>=1.0.53,<2.0.0)
Requires-Dist: paf_sapgui_cic (>=1.0.16,<2.0.0)
Requires-Dist: paf_tools (>=1.0.0,<2.0.0)
Requires-Dist: pendulum (>=2.1,<3.0)
